{
  "groups": [
    {
      "name": "group a",
      "teams": [],
      "winner": 2,
      "second": 14,
      "third": ""
    },
    {
      "name": "group b",
      "teams": [],
      "winner": 0,
      "second": 15,
      "third": ""
    },
    {
      "name": "group c",
      "teams": [],
      "winner": 12,
      "second": 3,
      "third": ""
    },
    {
      "name": "group d",
      "teams": [],
      "winner": 10,
      "second": 6,
      "third": ""
    },
    {
      "name": "group e",
      "teams": [],
      "winner": 8,
      "second": 7,
      "third": ""
    },
    {
      "name": "group f",
      "teams": [],
      "winner": 4,
      "second": 11,
      "third": "",
      "fourth": ""
    }
  ],
  "thirdTeams": ["", "", "", "", "", ""],
  "thirdPositions": [],
  "secondRound": [
    "",
    "",
    "",
    "",
    "",
    "",
    "",
    "",
    "",
    "",
    "",
    "",
    "",
    "",
    "",
    ""
  ],
  "quarters": [
    { "name": "quarter1", "home": "", "away": "" },
    {
      "name": "quarter2",
      "home": "",
      "away": ""
    },
    {
      "name": "quarter3",
      "home": "",
      "away": ""
    },
    {
      "name": "quarter4",
      "home": "",
      "away": ""
    }
  ],
  "semis": [
    { "name": "semi1", "home": "", "away": "" },
    {
      "name": "semi2",
      "home": "",
      "away": ""
    }
  ],
  "final": [{ "name": "final", "home": "", "away": "" }],
  "winner": []
}
